<videos type="array">
<video>
<version>1.0</version>
<id>21549069</id>
<title>TradingCentral财经电视2020年05月14日</title>
<description>美元震荡 黄金走软 </description>
<created_at>2020-05-14T18:12:00+00:00</created_at>
<url>https://view.vzaar.com/21549069/video</url>
<thumbnail_url>https://view.vzaar.com/21549069/thumb</thumbnail_url>
<image_url>https://view.vzaar.com/21549069/image</image_url>
<play_count>0</play_count>
<duration>94.1</duration>
<height>810</height>
<width>1440</width>
</video>
<video>
<version>1.0</version>
<id>21545540</id>
<title>现货黄金 (XAU) - 等待向上突破, 日内走势关键支持$1,705</title>
<description>
美联储主席Powell指没有正在考虑负利率, 但承认前景高度不确定及风险偏向下方. 另一方面, 美国联邦退休储蓄投资委员会表示将推迟旗下包括中国股票在内的基准指数的基金转换. 现货黄金日内走势稳步向上, 等待突破. 在关键支持$1,705之上, 上方目标在$1,723及$1,730. 反之, 跌破$1,705则预期拉回至$1,697及$1,690.
</description>
<created_at>2020-05-14T03:43:17+00:00</created_at>
<url>https://view.vzaar.com/21545540/video</url>
<thumbnail_url>https://view.vzaar.com/21545540/thumb</thumbnail_url>
<image_url>https://view.vzaar.com/21545540/image</image_url>
<play_count>0</play_count>
<duration>52.8</duration>
<height>720</height>
<width>1280</width>
</video>
<video>
<version>1.0</version>
<id>21544697</id>
<title>TradingCentral财经电视2020年05月13日</title>
<description>美元走强 黄金走软 </description>
<created_at>2020-05-13T20:19:33+00:00</created_at>
<url>https://view.vzaar.com/21544697/video</url>
<thumbnail_url>https://view.vzaar.com/21544697/thumb</thumbnail_url>
<image_url>https://view.vzaar.com/21544697/image</image_url>
<play_count>0</play_count>
<duration>94.8</duration>
<height>270</height>
<width>480</width>
</video>
</videos>